// class version 52.0 (52)
// access flags 0x31
public final class KotlinSortKt {

  // compiled from: KotlinSort.kt

  @Lkotlin/Metadata;(mv={1, 6, 0}, k=2, xi=48, d1={"\u0000\u0010\n\u0000\n\u0002\u0010\u0002\n\u0000\n\u0002\u0010\u0015\n\u0002\u0008\u0002\u001a\u000e\u0010\u0000\u001a\u00020\u00012\u0006\u0010\u0002\u001a\u00020\u0003\u001a\u0006\u0010\u0004\u001a\u00020\u0001\u00a8\u0006\u0005"}, d2={"bubblesort", "", "tab", "", "main", "lab3"})

  // access flags 0x19
  public final static bubblesort([I)V
    // annotable parameter count: 1 (invisible)
    @Lorg/jetbrains/annotations/NotNull;() // invisible, parameter 0
   L0
    ALOAD 0
    LDC "tab"
    INVOKESTATIC kotlin/jvm/internal/Intrinsics.checkNotNullParameter (Ljava/lang/Object;Ljava/lang/String;)V
   L1
    LINENUMBER 2 L1
    ICONST_0
    ISTORE 1
   L2
    ALOAD 0
    ARRAYLENGTH
    ISTORE 2
   L3
   FRAME APPEND [I I]
    ILOAD 1
    ILOAD 2
    IF_ICMPGE L4
   L5
    LINENUMBER 3 L5
    ICONST_0
    ISTORE 3
   L6
    ALOAD 0
    ARRAYLENGTH
    ICONST_1
    ISUB
    ISTORE 4
   L7
   FRAME APPEND [I I]
    ILOAD 3
    ILOAD 4
    IF_ICMPGE L8
   L9
    LINENUMBER 4 L9
    ALOAD 0
    ILOAD 3
    IALOAD
    ALOAD 0
    ILOAD 3
    ICONST_1
    IADD
    IALOAD
    IF_ICMPLE L10
   L11
    LINENUMBER 5 L11
    ALOAD 0
    ILOAD 3
    IALOAD
    ISTORE 5
   L12
    LINENUMBER 6 L12
    ALOAD 0
    ILOAD 3
    ALOAD 0
    ILOAD 3
    ICONST_1
    IADD
    IALOAD
    IASTORE
   L13
    LINENUMBER 7 L13
    ALOAD 0
    ILOAD 3
    ICONST_1
    IADD
    ILOAD 5
    IASTORE
   L10
    LINENUMBER 3 L10
   FRAME SAME
    IINC 3 1
    GOTO L7
   L8
    LINENUMBER 2 L8
   FRAME SAME
    IINC 1 1
    GOTO L3
   L4
    LINENUMBER 11 L4
   FRAME CHOP 2
    ICONST_0
    ISTORE 1
   L14
    ALOAD 0
    ARRAYLENGTH
    ISTORE 2
   L15
   FRAME SAME
    ILOAD 1
    ILOAD 2
    IF_ICMPGE L16
   L17
    LINENUMBER 12 L17
    NEW java/lang/StringBuilder
    DUP
    INVOKESPECIAL java/lang/StringBuilder.<init> ()V
    ALOAD 0
    ILOAD 1
    IALOAD
    INVOKEVIRTUAL java/lang/StringBuilder.append (I)Ljava/lang/StringBuilder;
    BIPUSH 32
    INVOKEVIRTUAL java/lang/StringBuilder.append (C)Ljava/lang/StringBuilder;
    INVOKEVIRTUAL java/lang/StringBuilder.toString ()Ljava/lang/String;
    GETSTATIC java/lang/System.out : Ljava/io/PrintStream;
    SWAP
    INVOKEVIRTUAL java/io/PrintStream.print (Ljava/lang/Object;)V
   L18
    LINENUMBER 11 L18
    IINC 1 1
    GOTO L15
   L16
    LINENUMBER 14 L16
   FRAME SAME
    RETURN
   L19
    LOCALVARIABLE temp I L12 L10 5
    LOCALVARIABLE j I L6 L8 3
    LOCALVARIABLE i I L2 L4 1
    LOCALVARIABLE i I L14 L16 1
    LOCALVARIABLE tab [I L0 L19 0
    MAXSTACK = 5
    MAXLOCALS = 6

  // access flags 0x19
  public final static main()V
   L0
    LINENUMBER 17 L0
    BIPUSH 10
    NEWARRAY T_INT
    ASTORE 1
    ALOAD 1
    ICONST_0
    ICONST_2
    IASTORE
    ALOAD 1
    ICONST_1
    ICONST_4
    IASTORE
    ALOAD 1
    ICONST_2
    SIPUSH 2137
    IASTORE
    ALOAD 1
    ICONST_3
    SIPUSH 420
    IASTORE
    ALOAD 1
    ICONST_4
    ICONST_2
    IASTORE
    ALOAD 1
    ICONST_5
    BIPUSH 68
    IASTORE
    ALOAD 1
    BIPUSH 6
    LDC 546423
    IASTORE
    ALOAD 1
    BIPUSH 7
    ICONST_3
    IASTORE
    ALOAD 1
    BIPUSH 8
    ICONST_4
    IASTORE
    ALOAD 1
    BIPUSH 9
    ICONST_5
    IASTORE
    ALOAD 1
    ASTORE 0
   L1
    LINENUMBER 18 L1
    ALOAD 0
    INVOKESTATIC KotlinSortKt.bubblesort ([I)V
   L2
    LINENUMBER 19 L2
    RETURN
   L3
    LOCALVARIABLE tab [I L1 L3 0
    MAXSTACK = 3
    MAXLOCALS = 2

  // access flags 0x1009
  public static synthetic main([Ljava/lang/String;)V
   L0
    INVOKESTATIC KotlinSortKt.main ()V
    RETURN
   L1
    LOCALVARIABLE args [Ljava/lang/String; L0 L1 0
    MAXSTACK = 0
    MAXLOCALS = 1
}
